sales_report/__main__.py
sales_report/sales_report.py
sales_report_bertollo-0.1.2.dist-info/METADATA
sales_report_bertollo-0.1.2.dist-info/WHEEL
sales_report_bertollo-0.1.2.dist-info/entry_points.txt
sales_report_bertollo-0.1.2.dist-info/top_level.txt
sales_report_bertollo-0.1.2.dist-info/RECORD
